pymitblod/__init__.py
pymitblod/donor.py
pymitblod/enums.py
pymitblod/gender.py
pymitblod/institution.py
pymitblod/mitblod.py
pymitblod/person.py
pymitblod/url.py
pymitblod/user.py
pymitblod-0.0.13.dist-info/LICENSE
pymitblod-0.0.13.dist-info/METADATA
pymitblod-0.0.13.dist-info/WHEEL
pymitblod-0.0.13.dist-info/top_level.txt
pymitblod-0.0.13.dist-info/RECORD
