Metadata-Version: 2.1
Name: pymitblod
Version: 0.0.13
Summary: API wrapper for blood donor webpages.
Home-page: https://github.com/slimcdk/pymitblod
Author: Christian Skjerning
Author-email: christian@skjerning.eu
License: Apache 2.0
Project-URL: Bug Tracker, https://github.com/slimcdk/pymitblod/issues
Platform: UNKNOWN
Classifier: Programming Language :: Python :: 3
Classifier: Operating System :: OS Independent
Requires-Python: >=3.6
License-File: LICENSE
Requires-Dist: requests (==2.26.0)
Requires-Dist: BeautifulSoup4 (==4.10.0)
